{"responses":{"200":{"description":"CreateDimension 200 response","content":{"application/json":{"schema":{"type":"object","properties":{"dimension":{"type":"string"},"position":{"type":"number"},"schema":{"type":"object","additionalProperties":{},"description":"Generic key-value object structure used for flexible data representation throughout the API.","title":"Object"},"value_validation_function_name":{"type":"string"},"description":{"type":"string"},"change_reason":{"type":"string"},"last_modified_at":{"type":"string","format":"date-time"},"last_modified_by":{"type":"string"},"created_at":{"type":"string","format":"date-time"},"created_by":{"type":"string"},"dependency_graph":{"type":"object","additionalProperties":{"type":"array","items":{"type":"string"}},"title":"DependencyGraph"},"dimension_type":{"oneOf":[{"type":"object","title":"REGULAR","properties":{"REGULAR":{"type":"object","title":"Unit"}},"required":["REGULAR"]},{"type":"object","title":"LOCAL_COHORT","properties":{"LOCAL_COHORT":{"type":"string"}},"required":["LOCAL_COHORT"]},{"type":"object","title":"REMOTE_COHORT","properties":{"REMOTE_COHORT":{"type":"string"}},"required":["REMOTE_COHORT"]}],"title":"DimensionType"},"value_compute_function_name":{"type":"string"},"mandatory":{"type":"boolean"}},"required":["change_reason","created_at","created_by","dependency_graph","description","dimension","dimension_type","last_modified_at","last_modified_by","mandatory","position","schema"],"title":"CreateDimensionResponseContent"}}}},"500":{"description":"InternalServerError 500 response","content":{"application/json":{"schema":{"type":"object","properties":{"message":{"type":"string"}},"title":"InternalServerErrorResponseContent"}}}}}}